requea_decoder/__init__.py
requea_decoder/decoder_factory.py
requea_decoder/decoders/__init__.py
requea_decoder/decoders/adeunis_decoder.py
requea_decoder/decoders/mclimate_decoder.py
requea_decoder/decoders/nexelec_decoder.py
requea_decoder/decoders/uplink_decoder.py
requea_decoder-0.0.5.dist-info/METADATA
requea_decoder-0.0.5.dist-info/WHEEL
requea_decoder-0.0.5.dist-info/top_level.txt
requea_decoder-0.0.5.dist-info/RECORD
